LICENSE.rst
MANIFEST.in
README.rst
setup.py
salesforce/__init__.py
salesforce/api.py
salesforce/exception.py
salesforce/httpClient.py
salesforce/login.py
salesforce/sObject.py
salesforce/salesforceApi.py
salesforce/salesforceRestApi.py
salesforce/salesforceSoapApi.py
salesforce/urlResources.py
salesforce/utils.py
salesforce/version.py
salesforce_python_sdk.egg-info/PKG-INFO
salesforce_python_sdk.egg-info/SOURCES.txt
salesforce_python_sdk.egg-info/dependency_links.txt
salesforce_python_sdk.egg-info/requires.txt
salesforce_python_sdk.egg-info/top_level.txt