Metadata-Version: 1.0
Name: salesforce-python-sdk
Version: 0.1.2
Summary: This is Salesforce Python SDK for REST and SOAP APIs
Home-page: https://github.com/htarevern/salesforce-python-sdk
Author: Hormoz Tarevern
Author-email: htarevern@yahoo.com
License: UNKNOWN
Keywords: Salesforce python sdk salesforce.com salesforce-python-sdk SalesforcePythonSDK
Platform: UNKNOWN
